ndxtest/__init__.py
ndxtest/backtest.py
ndxtest/dev.py
ndxtest/indicators.py
ndxtest/utils.py
ndxtest-0.0.2.dist-info/LICENSE
ndxtest-0.0.2.dist-info/METADATA
ndxtest-0.0.2.dist-info/WHEEL
ndxtest-0.0.2.dist-info/top_level.txt
ndxtest-0.0.2.dist-info/RECORD
