Metadata-Version: 2.1
Name: ndxtest
Version: 0.0.2
Summary: ndxtest lets you test trading strategies on the S&P 500.
Home-page: https://github.com/lksndx/ndxtest/
Author: lksdnx
Author-email: lukas.dnx@gmail.com
Classifier: Programming Language :: Python :: 3.9
Classifier: License :: OSI Approved :: MIT License
License-File: LICENSE
Requires-Dist: numpy (>=1.21.0)
Requires-Dist: pandas (>=1.3.0)
Requires-Dist: yfinance (>=0.1.74)
Requires-Dist: matplotlib (>=3.4.2)
Requires-Dist: fpdf (>=1.7.2)
Requires-Dist: openpyxl (>=3.0.7)
